{
  "id": null,
  "uid": "cLV5GDCkz",
  "title": "New dashboard",
  "tags": [],
  "style": "dark",
  "timezone": "browser",
  "editable": true,
  "hideControls": false,
  "graphTooltip": 1,
  "panels": [],
  "time": {
    "from": "now-6h",
    "to": "now"
  },
  "timepicker": {
    "time_options": [],
    "refresh_intervals": []
  },
  "templating": {
    "list": []
  },
  "annotations": {
    "list": []
  },
  "refresh": "5s",
  "schemaVersion": 17,
  "version": 0,
  "links": [],
  "panels": [
      {
        "datasource": "loki",
        "type": "logs",
        "title": "Logs",
        "targets": [
          {
            "expr": "{filename=\"/tmp/app-logs/access.log\"} |= \"\"",
            "refId": "A"
          }
        ],
        "gridPos": {
          "h": 10,
          "w": 24,
          "x": 0,
          "y": 0
        },
        "options": {
          "showLabels": true,
          "showTime": true,
          "wrapLogMessage": true
        }
      }
    ],
}
